pbest/__init__.py
pbest/globals.py
pbest/main.py
pbest/py.typed
pbest/containerization/__init__.py
pbest/containerization/container_constructor.py
pbest/containerization/containerization_cli.py
pbest/containerization/generic_container.jinja
pbest/dependency_resolution/__init__.py
pbest/dependency_resolution/discovery.py
pbest/dependency_resolution/whitelist.py
pbest/registry/__init__.py
pbest/registry/comparison.py
pbest/registry/local_registry.py
pbest/registry/stats.py
pbest/registry/utils.py
pbest/registry/simulators/__init__.py
pbest/registry/simulators/copasi_process.py
pbest/registry/simulators/tellurium_process.py
pbest/registry/simulators/test.py
pbest/utils/__init__.py
pbest/utils/builder.py
pbest/utils/experiment_archive.py
pbest/utils/input_types.py
pbest-0.2.6.dist-info/METADATA
pbest-0.2.6.dist-info/WHEEL
pbest-0.2.6.dist-info/licenses/LICENSE
pbest-0.2.6.dist-info/RECORD
