Metadata-Version: 2.4
Name: pbest
Version: 0.2.6
Summary: BioSim Registry is a project focused on delivering high quality processes and tooling in relation to process bi-graph.
Project-URL: Homepage, https://github.com/biosimulations/biosim-registry/
Project-URL: Repository, https://github.com/biosimulations/biosim-registry/
Project-URL: Documentation, https://github.com/biosimulations/biosim-registry/
Author-email: Center for Reproducable Biological Modeling <evalencia@uchc.edu>
License-File: LICENSE
Keywords: python
Classifier: Intended Audience :: Developers
Classifier: Programming Language :: Python
Classifier: Programming Language :: Python :: 3
Classifier: Programming Language :: Python :: 3.11
Classifier: Programming Language :: Python :: 3.12
Classifier: Programming Language :: Python :: 3.13
Classifier: Topic :: Software Development :: Libraries :: Python Modules
Requires-Python: <3.13,>=3.11
Requires-Dist: bigraph-schema==0.0.77
Requires-Dist: copasi-basico
Requires-Dist: jinja2>=3.1.6
Requires-Dist: libroadrunner
Requires-Dist: matplotlib
Requires-Dist: numpy>=2.3.4
Requires-Dist: pandas>=2.3.3
Requires-Dist: process-bigraph==0.0.51
Requires-Dist: pydantic>=2.12.3
Requires-Dist: python-copasi
Requires-Dist: spython>=0.3.14
Requires-Dist: tellurium>=2.2.11.1
